imdix/__init__.py
imdix/main.py
imdix/utils.py
imdix-0.0.4.dist-info/METADATA
imdix-0.0.4.dist-info/WHEEL
imdix-0.0.4.dist-info/entry_points.txt
imdix-0.0.4.dist-info/top_level.txt
imdix-0.0.4.dist-info/RECORD
