Metadata-Version: 2.1
Name: imdix
Version: 0.0.4
Summary: Dynamic image resizing tool
Home-page: https://github.com/amalshaji/imdix
Author: Amal Shaji
Author-email: amalshajid@tutanota.com
License: MIT
Platform: UNKNOWN
Classifier: License :: OSI Approved :: MIT License
Classifier: Programming Language :: Python :: 3
Classifier: Programming Language :: Python :: 3.8
Classifier: Operating System :: OS Independent
Requires-Dist: opencv-python
